ecodatatk/Spatial.py
ecodatatk/__init__.py
ecodatatk-0.0.1.dist-info/LICENSE
ecodatatk-0.0.1.dist-info/METADATA
ecodatatk-0.0.1.dist-info/WHEEL
ecodatatk-0.0.1.dist-info/top_level.txt
ecodatatk-0.0.1.dist-info/RECORD
